Metadata-Version: 1.2
Name: vsgen-ptvs
Version: 0.1.4
Summary: An extension for the VSGen solution and project generator that defines projects and solutions for Python Tools for Visual Studio.
Home-page: https://github.com/dbarsam/python-vsgen-ptvs
Author: dbarsam
Author-email: dbarsam@gmail.com
License: MIT
Keywords: visual studio project generation
Platform: UNKNOWN
Classifier: Development Status :: 4 - Beta
Classifier: Environment :: Console
Classifier: Intended Audience :: Developers
Classifier: Topic :: Software Development 
Classifier: License :: OSI Approved :: MIT License
Classifier: Programming Language :: Python :: 2.7
Classifier: Programming Language :: Python :: 3.6
Classifier: Topic :: Office/Business :: Groupware
Requires-Python: >=2.7,!=3.0.*,!=3.1.*,!=3.2.*,!=3.3.*
